effimemo/__init__.py
effimemo/manager.py
effimemo/adapters/__init__.py
effimemo/adapters/openai.py
effimemo/core/__init__.py
effimemo/core/tokenizer.py
effimemo/strategies/__init__.py
effimemo/strategies/base.py
effimemo/strategies/compression.py
effimemo/strategies/summary.py
effimemo/strategies/truncation.py
effimemo-0.1.0.dist-info/licenses/LICENSE
effimemo-0.1.0.dist-info/METADATA
effimemo-0.1.0.dist-info/WHEEL
effimemo-0.1.0.dist-info/top_level.txt
effimemo-0.1.0.dist-info/RECORD
