Metadata-Version: 2.4
Name: effimemo
Version: 0.1.0
Summary: A Python package for managing LLM context windows
Home-page: https://github.com/betterandbetteri/effimemo
Author: betterandbetterii
Author-email: betterandbetterii <betterandbetterii@gmail.com>
Maintainer-email: betterandbetterii <betterandbetterii@gmail.com>
License: MIT
Project-URL: Homepage, https://github.com/betterandbetteri/effimemo
Project-URL: Repository, https://github.com/betterandbetteri/effimemo
Project-URL: Issues, https://github.com/betterandbetteri/effimemo/issues
Keywords: llm,context,management,token,window,ai,chatbot
Classifier: Development Status :: 4 - Beta
Classifier: Intended Audience :: Developers
Classifier: Programming Language :: Python :: 3
Classifier: Programming Language :: Python :: 3.8
Classifier: Programming Language :: Python :: 3.9
Classifier: Programming Language :: Python :: 3.10
Classifier: Programming Language :: Python :: 3.11
Classifier: Programming Language :: Python :: 3.12
Classifier: Topic :: Software Development :: Libraries :: Python Modules
Classifier: Topic :: Scientific/Engineering :: Artificial Intelligence
Requires-Python: >=3.8
License-File: LICENSE
Requires-Dist: tiktoken>=0.5.0
Provides-Extra: dev
Requires-Dist: pytest>=7.0; extra == "dev"
Requires-Dist: pytest-cov>=4.0; extra == "dev"
Requires-Dist: black>=23.0; extra == "dev"
Requires-Dist: isort>=5.0; extra == "dev"
Requires-Dist: flake8>=6.0; extra == "dev"
Provides-Extra: openai
Requires-Dist: openai>=1.0.0; extra == "openai"
Provides-Extra: compression
Requires-Dist: selective-context>=1.0.0; extra == "compression"
Dynamic: author
Dynamic: home-page
Dynamic: license-file
Dynamic: requires-python
